bee/__init__.py
bee/active_record.py
bee/api.py
bee/assist_api.py
bee/bee_enum.py
bee/condition.py
bee/config.py
bee/conn_builder.py
bee/context.py
bee/custom.py
bee/exception.py
bee/factory.py
bee/helper.py
bee/honeyfactory.py
bee/typing.py
bee/util.py
bee/version.py
bee/name/NameCheckUtil.py
bee/name/NameUtil.py
bee/name/__init__.py
bee/name/bloom.py
bee/name/naming.py
bee/name/naming_handler.py
bee/osql/SqlUtil.py
bee/osql/Util.py
bee/osql/__init__.py
bee/osql/base.py
bee/osql/cache.py
bee/osql/condition_impl.py
bee/osql/const.py
bee/osql/engine.py
bee/osql/gen.py
bee/osql/index.py
bee/osql/logger.py
bee/osql/mid.py
bee/osql/mid_typing.py
bee/osql/obj2sql.py
bee/osql/paging.py
bee/osql/sqlkeyword.py
bee/osql/sqllib.py
bee/osql/struct.py
bee/osql/transform.py
bee/osql/type_transform.py
ormbee-1.6.8.dist-info/METADATA
ormbee-1.6.8.dist-info/WHEEL
ormbee-1.6.8.dist-info/licenses/LICENSE
ormbee-1.6.8.dist-info/RECORD
