Metadata-Version: 2.4
Name: ormbee
Version: 1.6.8
Summary: Bee(BeePy) is an ORM tool with Python.
Project-URL: Homepage, https://github.com/automvc/BeePy
Project-URL: Issues, https://github.com/automvc/BeePy/issues
Project-URL: Repository, https://github.com/automvc/BeePy.git
Project-URL: Changelog, https://github.com/automvc/BeePy/blob/master/CHANGELOG.md
Author-email: AiTeaSoft <aiteasoft@126.com>, Kingstar <honeysoft@126.com>
Maintainer-email: AiTeaSoft <aiteasoft@126.com>, Kingstar <honeysoft@126.com>
License:                                  Apache License
License-File: LICENSE
Keywords: Bee,BeePy,DB,ORM,Oracle,dao,database,db,ormbee,psycopg2,pymysql,sqlite3
Classifier: Operating System :: OS Independent
Classifier: Programming Language :: Python :: 3
Requires-Python: >=3.8.10
